toymcp/Functions.py
toymcp/RemoteMCP.py
toymcp/StopFunction.py
toymcp-0.1.0.dist-info/METADATA
toymcp-0.1.0.dist-info/WHEEL
toymcp-0.1.0.dist-info/top_level.txt
toymcp-0.1.0.dist-info/RECORD
