Metadata-Version: 2.4
Name: toymcp
Version: 0.1.0
Summary: Add your description here
Requires-Python: >=3.12
Requires-Dist: mcp>=1.10.1
Requires-Dist: requests>=2.32.4
